sanic_amqp_ext/__init__.py
sanic_amqp_xtension-0.1.3.dist-info/LICENSE
sanic_amqp_xtension-0.1.3.dist-info/METADATA
sanic_amqp_xtension-0.1.3.dist-info/WHEEL
sanic_amqp_xtension-0.1.3.dist-info/top_level.txt
sanic_amqp_xtension-0.1.3.dist-info/RECORD
