Metadata-Version: 2.1
Name: sanic-amqp-xtension
Version: 0.1.3
Summary: AMQP support for Sanic framework
Home-page: https://github.com/openwhalereef/sanic-amqp-extension
Author: Open Whalereef
Author-email: open@whalereef.com
License: BSD
Platform: any
Classifier: Environment :: Web Environment
Classifier: License :: OSI Approved :: BSD License
Classifier: Intended Audience :: Developers
Classifier: Programming Language :: Python
Classifier: Programming Language :: Python :: 3
Classifier: Programming Language :: Python :: 3.5
Classifier: Programming Language :: Python :: 3.6
Classifier: Programming Language :: Python :: 3.7
Classifier: Topic :: Software Development :: Libraries :: Python Modules
Requires-Dist: sanic-base-extension (==0.1.1)
Requires-Dist: aioamqp (==0.14.0)
